collectors_channel_cli/__init__.py
collectors_channel_cli/main.py
collectors_channel_cli-1.8.0.dist-info/LICENSE
collectors_channel_cli-1.8.0.dist-info/METADATA
collectors_channel_cli-1.8.0.dist-info/WHEEL
collectors_channel_cli-1.8.0.dist-info/entry_points.txt
collectors_channel_cli-1.8.0.dist-info/RECORD
