Metadata-Version: 2.1
Name: collectors-channel-cli
Version: 1.8.0
Summary: 
Author: Paulo Salgado
Author-email: pjosalgado@gmail.com
Requires-Python: >=3.8,<4.0
Classifier: Programming Language :: Python :: 3
Classifier: Programming Language :: Python :: 3.8
Classifier: Programming Language :: Python :: 3.9
Classifier: Programming Language :: Python :: 3.10
Classifier: Programming Language :: Python :: 3.11
Requires-Dist: dnspython (>=2.1.0,<3.0.0)
Requires-Dist: pymongo (>=3.11.3,<4.0.0)
Requires-Dist: python-dotenv (>=0.15.0,<0.16.0)
Requires-Dist: typer[all] (>=0.3.2,<0.4.0)
